zha_quirks-0.0.154.dist-info/licenses/LICENSE.md
zhaquirks/__init__.py
zhaquirks/const.py
zhaquirks/quirk_ids.py
zhaquirks/adeo/__init__.py
zhaquirks/adeo/color_controller.py
zhaquirks/aduro/__init__.py
zhaquirks/aduro/adurolightncc.py
zhaquirks/aurora/__init__.py
zhaquirks/aurora/aurora_dimmer.py
zhaquirks/bitron/__init__.py
zhaquirks/bitron/thermostat.py
zhaquirks/bosch/__init__.py
zhaquirks/bosch/isw_zdl1_wp11g.py
zhaquirks/bosch/motion.py
zhaquirks/bosch/rbsh_rth0_zb_eu.py
zhaquirks/bosch/rbsh_trv0_zb_eu.py
zhaquirks/bosch/relay_rbsh-mms-zb-eu.py
zhaquirks/candeo/__init__.py
zhaquirks/candeo/rotary_dimmer_switches.py
zhaquirks/candeo/sensors.py
zhaquirks/candeo/smart_led_controllers.py
zhaquirks/candeo/wall_modules.py
zhaquirks/centralite/__init__.py
zhaquirks/centralite/cl_3130.py
zhaquirks/centralite/cl_3157100.py
zhaquirks/centralite/cl_3300S.py
zhaquirks/centralite/cl_3305S.py
zhaquirks/centralite/cl_3310S.py
zhaquirks/centralite/cl_3321S.py
zhaquirks/centralite/cl_3460L.py
zhaquirks/centralite/ias.py
zhaquirks/centralite/motion.py
zhaquirks/centralite/motionandtemp.py
zhaquirks/custom/__init__.py
zhaquirks/custom/telink.py
zhaquirks/danfoss/__init__.py
zhaquirks/danfoss/thermostat.py
zhaquirks/develco/__init__.py
zhaquirks/develco/air_quality.py
zhaquirks/develco/emi_han.py
zhaquirks/develco/emi_led.py
zhaquirks/develco/emi_p1.py
zhaquirks/develco/heat_alarm.py
zhaquirks/develco/humidity.py
zhaquirks/develco/intelligent_keypad.py
zhaquirks/develco/io_module.py
zhaquirks/develco/motion.py
zhaquirks/develco/open_close.py
zhaquirks/develco/power_plug.py
zhaquirks/develco/smart_button.py
zhaquirks/develco/smart_siren.py
zhaquirks/develco/smoke_alarm.py
zhaquirks/develco/water_leak.py
zhaquirks/echostar/__init__.py
zhaquirks/echostar/bell.py
zhaquirks/ecolink/__init__.py
zhaquirks/ecolink/contact.py
zhaquirks/edpwithus/__init__.py
zhaquirks/edpwithus/redy_plug.py
zhaquirks/elko/__init__.py
zhaquirks/elko/smart_super_thermostat.py
zhaquirks/eurotronic/__init__.py
zhaquirks/eurotronic/spzb0001.py
zha_quirks-0.0.154.dist-info/METADATA
zha_quirks-0.0.154.dist-info/WHEEL
zha_quirks-0.0.154.dist-info/top_level.txt
zha_quirks-0.0.154.dist-info/RECORD
