Metadata-Version: 2.4
Name: zha-quirks
Version: 0.0.154
Summary: Library implementing Zigpy quirks for ZHA in Home Assistant
Author-email: "David F. Mulcahey" <david.mulcahey@icloud.com>
License: Apache-2.0
Project-URL: repository, https://github.com/zigpy/zha-device-handlers
Requires-Python: >=3.12
License-File: LICENSE.md
Requires-Dist: zigpy>=0.91.5
Dynamic: license-file
